openai_moonsun_utils/__init__.py
openai_moonsun_utils/main.py
openai_moonsun_utils-0.1.3.dist-info/licenses/LICENSE.txt
openai_moonsun_utils-0.1.3.dist-info/METADATA
openai_moonsun_utils-0.1.3.dist-info/WHEEL
openai_moonsun_utils-0.1.3.dist-info/entry_points.txt
openai_moonsun_utils-0.1.3.dist-info/top_level.txt
openai_moonsun_utils-0.1.3.dist-info/RECORD
