Metadata-Version: 2.4
Name: openai_moonsun_utils
Version: 0.1.3
Summary: Add a short description here!
Home-page: https://github.com/odoonix/openai-utils
Author: MoonSun
Author-email: info@moonsun.au
License: MIT
Project-URL: Documentation, https://github.com/odoonix/openai-utils
Project-URL: Source, https://github.com/odoonix/openai-utils
Platform: any
Classifier: Development Status :: 4 - Beta
Classifier: Programming Language :: Python
License-File: LICENSE.txt
Requires-Dist: importlib-metadata; python_version < "3.8"
Requires-Dist: typer
Provides-Extra: testing
Requires-Dist: setuptools; extra == "testing"
Requires-Dist: pytest; extra == "testing"
Requires-Dist: pytest-cov; extra == "testing"
Dynamic: license-file
